{
  "type": "object",
  "properties": {
    "ok": {
      "required": true,
      "type": "boolean"
    },
    "version": {
      "required": true,
      "type": "string",
      "format": "semver"
    },
    "api-version": {
      "required": true,
      "type": "string",
      "format": "semver"
    },
    "errorText": {
      "required": false,
      "type": "string"
    },
    "errorLog": {
      "required": false,
      "type": "array",
      "items": {
        "type": "string"
      }
    }
  },
  "additionalProperties": true
}
